{
    "dsbm_cycle": {
        "k": 5,
        "n_per_class": 100,
        "p": 0.3,
        "s": 0.1,
        "r": 0.05
    },
    "dsbm_cycle_general": {
        "k": 5,
        "n_per_class": 100,
        "p": 0.2,
        "fwd": [0.2, 0.1, 0.3, 0.1, 0.15],
        "bwd": [0.1, 0.05, 0.05, 0.02, 0.1],
        "r": 0.02
    },
    "nested_dsbm_cycle": {
        "c1": 5,
        "c2": 3,
        "n_per_block": 50,
        "p": 0.2,
        "s_inner": 0.2,
        "s_outer": 0.2,
        "r": 0.05
    },
    "directed_small_world": {
        "n": 300,
        "k": 4,
        "p": 0.1
    }
}
